{
  "run_number": 14,
  "run_id": "26206397334",
  "timestamp": "2026-05-21T05:25:36+00:00",
  "commit": "5e7d34b",
  "ragas": {
    "avg_faithfulness": 0.944,
    "avg_relevancy": 0.787,
    "status": "fail"
  },
  "giskard_rag": {},
  "giskard_scan": {
    "rag_api": "https://alexpavsky.com",
    "categories": [
      "hallucination",
      "injection",
      "harmfulness",
      "stereotypes",
      "robustness",
      "sensitive_topics",
      "jailbreak"
    ],
    "judge": "groq/llama-3.3-70b-versatile",
    "total_issues": 5,
    "issues_by_category": {
      "hallucination": 1,
      "injection": 2,
      "harmfulness": 1,
      "stereotypes": 0,
      "robustness": 1,
      "sensitive_topics": 0,
      "jailbreak": 0
    }
  },
  "files": [
    "report.md",
    "giskard_scan.html",
    "giskard_scan.json"
  ]
}